[
  {
    "img": "img/banner1.jpg",
    "title": "珠峰培训",
    "link": "http://www.zhufengpeixun.cn/"
  },
  {
    "img": "img/banner2.jpg",
    "title": "珠峰培训",
    "link": "http://www.zhufengpeixun.cn/"
  },
  {
    "img": "img/banner3.jpg",
    "title": "珠峰培训",
    "link": "http://www.zhufengpeixun.cn/"
  },
  {
    "img": "img/banner4.jpg",
    "title": "珠峰培训",
    "link": "http://www.zhufengpeixun.cn/"
  },
  {
    "img": "img/banner5.jpg",
    "title": "珠峰培训",
    "link": "http://www.zhufengpeixun.cn/"
  }
]